advent_of_code_ocr/__init__.py
advent_of_code_ocr/__main__.py
advent_of_code_ocr/characters.py
advent_of_code_ocr/cli.py
advent_of_code_ocr/exceptions.py
advent_of_code_ocr/height_6.py
advent_of_code_ocr-1.1.0.dist-info/METADATA
advent_of_code_ocr-1.1.0.dist-info/WHEEL
advent_of_code_ocr-1.1.0.dist-info/licenses/LICENSE
advent_of_code_ocr-1.1.0.dist-info/RECORD
