Metadata-Version: 2.4
Name: advent-of-code-ocr
Version: 1.1.0
Summary: A library to parse Advent of Code ASCII art
Project-URL: Changelog, https://github.com/bsoyka/advent-of-code-ocr/releases
Project-URL: Source, https://github.com/bsoyka/advent-of-code-ocr
Author-email: Ben Soyka <hello@bsoyka.me>
License-File: LICENSE
Classifier: Development Status :: 5 - Production/Stable
Classifier: Intended Audience :: Developers
Classifier: License :: OSI Approved :: MIT License
Classifier: Natural Language :: English
Classifier: Programming Language :: Python
Classifier: Programming Language :: Python :: 3
Classifier: Programming Language :: Python :: 3.10
Classifier: Programming Language :: Python :: 3.11
Classifier: Programming Language :: Python :: 3.12
Classifier: Programming Language :: Python :: 3.13
Requires-Python: >=3.10
Requires-Dist: click>=8.2.1
